{
  "id": {
    "entityType": "WIDGET_TYPE",
    "id": "7bd448d0-b418-11f0-b467-01a4a84a7779"
  },
  "createdTime": 1761667769821,
  "tenantId": {
    "entityType": "TENANT",
    "id": "13814000-1dd2-11b2-8080-808080808080"
  },
  "fqn": "hp_large_inverter",
  "name": "HP Large inverter",
  "deprecated": false,
  "scada": true,
  "version": 1,
  "image": "tb-image;/api/images/system/large-inverter-hp.svg",
  "description": "Large inverter with various states.",
  "tags": [
    "energy",
    "power",
    "hybrid",
    "solar",
    "backup"
  ],
  "widgetType": "rpc",
  "bundles": [
    {
      "id": {
        "entityType": "WIDGETS_BUNDLE",
        "id": "7d1e06e0-b418-11f0-b467-01a4a84a7779"
      },
      "name": "High-performance SCADA energy system"
    }
  ]
}