{
  "id": {
    "entityType": "WIDGET_TYPE",
    "id": "7bfbce00-b418-11f0-b467-01a4a84a7779"
  },
  "createdTime": 1761667770080,
  "tenantId": {
    "entityType": "TENANT",
    "id": "13814000-1dd2-11b2-8080-808080808080"
  },
  "fqn": "large_stand_cylindrical_tank",
  "name": "Large stand cylindrical tank",
  "deprecated": false,
  "scada": true,
  "version": 1,
  "image": "tb-image;/api/images/system/large-stand-cylindrical-tank.svg",
  "description": "Large stand cylindrical tank with current volume value and level visualizations.",
  "tags": [
    "tank",
    "stand tank"
  ],
  "widgetType": "rpc",
  "bundles": [
    {
      "id": {
        "entityType": "WIDGETS_BUNDLE",
        "id": "7e136360-b418-11f0-b467-01a4a84a7779"
      },
      "name": "Traditional SCADA fluid system"
    }
  ]
}